desktop_banner/__init__.py
desktop_banner/banner.py
desktop_banner-0.0.1.data/scripts/banner
desktop_banner-0.0.1.dist-info/LICENSE
desktop_banner-0.0.1.dist-info/METADATA
desktop_banner-0.0.1.dist-info/WHEEL
desktop_banner-0.0.1.dist-info/top_level.txt
desktop_banner-0.0.1.dist-info/RECORD
